pytiktok/__init__.py
pytiktok/business_account_api.py
pytiktok/error.py
pytiktok/kit_api.py
pytiktok/models/__init__.py
pytiktok/models/base.py
pytiktok/models/business_account.py
pytiktok/models/kit.py
python_tiktok-0.1.11.dist-info/LICENSE
python_tiktok-0.1.11.dist-info/METADATA
python_tiktok-0.1.11.dist-info/WHEEL
python_tiktok-0.1.11.dist-info/RECORD
