Metadata-Version: 2.3
Name: python-tiktok
Version: 0.1.11
Summary: A simple Python wrapper for Tiktok API. ✨ 🍰 ✨
License: MIT
Keywords: tiktok,tiktok sdk,tiktok api
Author: ikaroskun
Author-email: merle.liukun@gmail.com
Requires-Python: >=3.7,<4.0
Classifier: Intended Audience :: Developers
Classifier: License :: OSI Approved :: MIT License
Classifier: Programming Language :: Python :: 3
Classifier: Programming Language :: Python :: 3.7
Classifier: Programming Language :: Python :: 3.8
Classifier: Programming Language :: Python :: 3.9
Classifier: Programming Language :: Python :: 3.10
Classifier: Programming Language :: Python :: 3.11
Classifier: Programming Language :: Python :: 3.12
Classifier: Programming Language :: Python :: 3.13
Classifier: Programming Language :: Python :: Implementation :: CPython
Classifier: Topic :: Software Development :: Libraries :: Python Modules
Requires-Dist: dataclasses-json (>=0.6.0,<0.7.0)
Requires-Dist: requests (>=2.24,<3.0)
Project-URL: Repository, https://github.com/sns-sdks/python-tiktok
